diff_kit/__init__.py
diff_kit/db_diff/__init__.py
diff_kit/db_diff/core/__init__.py
diff_kit/db_diff/core/compare_data.py
diff_kit/db_diff/core/results.py
diff_kit/db_diff/db_engine/__init__.py
diff_kit/db_diff/db_engine/abc.py
diff_kit/db_diff/db_engine/exception.py
diff_kit/db_diff/db_engine/mysql.py
diff_kit/db_diff/db_engine/pgsql.py
diff_kit/db_diff/report/__init__.py
diff_kit/db_diff/report/excel_report.py
diff_kit/db_diff/report/report_factory.py
diff_kit/db_diff/report/text_report.py
diff_kit/utils/__init__.py
diff_kit/utils/logger.py
diff_kit-0.1.5.dist-info/LICENSE
diff_kit-0.1.5.dist-info/METADATA
diff_kit-0.1.5.dist-info/WHEEL
diff_kit-0.1.5.dist-info/top_level.txt
diff_kit-0.1.5.dist-info/RECORD
