Metadata-Version: 2.1
Name: diff-kit
Version: 0.1.5
Summary: 对比工具集
Home-page: https://gitee.com/Test-Alan/diff-kit
Author: alan
Author-email: 280262569@qq.com
License: Apache License 2.0
Keywords: diff mysql db
Classifier: Development Status :: 3 - Alpha
Classifier: License :: OSI Approved :: Apache Software License
Classifier: Programming Language :: Python
Classifier: Programming Language :: Python :: 3
Classifier: Programming Language :: Python :: 3.8
Classifier: Programming Language :: Python :: 3.9
Classifier: Programming Language :: Python :: 3.10
Classifier: Programming Language :: Python :: 3.11
Requires-Python: >=3.8
License-File: LICENSE
Requires-Dist: typer
Requires-Dist: rich
Requires-Dist: dictdiffer
Requires-Dist: loguru
Requires-Dist: aiomysql
Requires-Dist: motor
Requires-Dist: asyncpg
Requires-Dist: pandas
Requires-Dist: openpyxl
Requires-Dist: tqdm
Requires-Dist: pydantic
